README.md
setup.py
PyFNBR.egg-info/PKG-INFO
PyFNBR.egg-info/SOURCES.txt
PyFNBR.egg-info/dependency_links.txt
PyFNBR.egg-info/requires.txt
PyFNBR.egg-info/top_level.txt
fnbr/__init__.py
fnbr/models.py