Metadata-Version: 2.1
Name: PyFNBR
Version: 1.0.1
Summary: Python API wrapper for the FNBR.co API
Home-page: https://github.com/JustMaffie/PyFNBR
Author: JustMaffie
License: AGPL
Project-URL: Documentation, https://github.com/JustMaffie/PyFNBR/wiki
Project-URL: Source, https://github.com/JustMaffie/PyFNBR
Keywords: API fortnite fnbr fnbr.co
Platform: UNKNOWN
